Dustvw/Dustvw.py
Dustvw/__init__.py
Dustvw-0.2.2.dist-info/METADATA
Dustvw-0.2.2.dist-info/WHEEL
Dustvw-0.2.2.dist-info/top_level.txt
Dustvw-0.2.2.dist-info/RECORD
