Metadata-Version: 2.1
Name: Dustvw
Version: 0.2.2
Summary: Fine dust visualization
Home-page: https://github.com/Pandemic23/Dustvw-ver1.5
Author: Youngco
Author-email: popofh12345@naver.com
Classifier: Programming Language :: Python :: 3
Classifier: License :: OSI Approved :: MIT License
Classifier: Operating System :: OS Independent
Requires-Dist: Folium
Requires-Dist: pandas
